deepctr_torch/__init__.py
deepctr_torch/callbacks.py
deepctr_torch/inputs.py
deepctr_torch/utils.py
deepctr_torch/layers/__init__.py
deepctr_torch/layers/activation.py
deepctr_torch/layers/core.py
deepctr_torch/layers/interaction.py
deepctr_torch/layers/sequence.py
deepctr_torch/layers/utils.py
deepctr_torch/models/__init__.py
deepctr_torch/models/afm.py
deepctr_torch/models/afn.py
deepctr_torch/models/autoint.py
deepctr_torch/models/basemodel.py
deepctr_torch/models/ccpm.py
deepctr_torch/models/dcn.py
deepctr_torch/models/dcnmix.py
deepctr_torch/models/deepfm.py
deepctr_torch/models/dien.py
deepctr_torch/models/difm.py
deepctr_torch/models/din.py
deepctr_torch/models/fibinet.py
deepctr_torch/models/ifm.py
deepctr_torch/models/mlr.py
deepctr_torch/models/nfm.py
deepctr_torch/models/onn.py
deepctr_torch/models/pnn.py
deepctr_torch/models/wdl.py
deepctr_torch/models/xdeepfm.py
deepctr_torch/models/multitask/__init__.py
deepctr_torch/models/multitask/esmm.py
deepctr_torch/models/multitask/mmoe.py
deepctr_torch/models/multitask/ple.py
deepctr_torch/models/multitask/sharedbottom.py
tests/models/multitask/ESMM_test.py
tests/models/multitask/MMOE_test.py
tests/models/multitask/PLE_test.py
tests/models/multitask/SharedBottom_test.py
tests/models/multitask/__init__.py
deepctr_torch-0.2.9.dist-info/LICENSE
deepctr_torch-0.2.9.dist-info/METADATA
deepctr_torch-0.2.9.dist-info/WHEEL
deepctr_torch-0.2.9.dist-info/top_level.txt
deepctr_torch-0.2.9.dist-info/RECORD
